[
  {
    "id": "666b048b-eb37-43a6-befa-45f01c831d2b",
    "org": "SQUIZ Online",
    "image": "squiz.png",
    "url": ["https://online.squiz.ru/#schedule"],
    "latestCheck": "2023-02-19T12:00:00+03:00",
    "latestGame": "2022-12-17T03:00:00+03:00",
    "priority": 200,
    "price": ["1500 RUB/ком"],
    "info": ["Ссылки выдаются перед игрой, вопросы вводятся на сайт, около 50 вопросов за игру."],
    "games": [
      {"time": "2022-12-02T19:30:00+03:00", "name": "Лига новичков. Игра 11"},
      {"time": "2022-12-03T17:00:00+03:00", "name": "Игра 240"},
      {"time": "2022-12-10T20:00:00+03:00", "name": "Лига новичков. Игра 12"},
      {"time": "2022-12-17T20:00:00+03:00", "name": "18+. Игра 9"},
      {"time": "2022-12-24T20:00:00+03:00", "name": "Игра 241"},
      {"time": "2023-01-13T19:30:00+03:00", "name": "Игра 242"},
      {"time": "2023-01-14T17:00:00+03:00", "name": "Игра 243"},
      {"time": "2023-01-19T20:00:00+03:00", "name": "Игра 244"},
      {"time": "2023-01-21T17:00:00+03:00", "name": "18+. Игра 9"},
      {"time": "2023-01-25T20:00:00+03:00", "name": "Игра 245"},
      {"time": "2023-01-28T20:00:00+03:00", "name": "Лига новичков. Игра 13"},
      {"time": "2023-02-03T20:00:00+03:00", "name": "Игра 246"},
      {"time": "2023-02-04T20:00:00+03:00", "name": "Игра 247"},
      {"time": "2023-02-10T20:00:00+03:00", "name": "Сериалы. Кино. Музыка. Игра 20"},
      {"time": "2023-02-11T20:00:00+03:00", "name": "Игра 248"},
      {"time": "2023-02-14T20:00:00+03:00", "name": "18+. Игра 10"},
      {"time": "2023-02-18T20:00:00+03:00", "name": "Игра 249"},
      {"time": "2023-02-25T20:00:00+03:00", "name": "Игра 250"},
      {"time": "2023-03-02T20:00:00+03:00", "name": "Игра 251"},
      {"time": "2023-03-04T20:00:00+03:00", "name": "Игра 252"}
    ]
  }
]
