[
  {
    "org": "Мозгобойня",
    "latestCheck": "2020-05-01T12:00:00+03:00",
    "type": ["events"],
    "image": "mzgb.png",
    "duration": 1.5,
    "url": ["https://taplink.cc/mzgb_msk", "https://live.mozgo.com"],
    "games": [
      {
        "time": "2020-04-11T18:00:00+03:00",
        "name": "MozgoCash: привет из 90-х",
        "price": ["399 RUB/ком"],
        "url": ["https://quizy.pro/streams/1829"]
      },
      {
        "time": "2020-04-12T14:00:00+03:00",
        "name": "MozgoCash: классическая игра",
        "price": ["399 RUB/ком"],
        "url": ["https://quizy.pro/streams/1830"]
      },
      {
        "time": "2020-04-12T18:00:00+03:00",
        "name": "MozgoCash: классическая игра",
        "price": ["399 RUB/ком"],
        "url": ["https://quizy.pro/streams/1831"]
      },
      {
        "time": "2020-04-14T18:30:00+03:00",
        "name": "Мозгобойня live",
        "price": ["899 RUB/ком"]
      },
      {
        "time": "2020-04-15T19:00:00+03:00",
        "name": "MozgoCash: 18+",
        "price": ["399 RUB/ком"],
        "url": ["https://quizy.pro/streams/1912"]
      },
      {
        "time": "2020-04-17T18:30:00+03:00",
        "name": "Мозгобойня live",
        "price": ["899 RUB/ком"]
      },
      {
        "time": "2020-04-18T18:00:00+03:00",
        "name": "MozgoCash: классическая игра",
        "price": ["399 RUB/ком"],
        "url": ["https://quizy.pro/streams/1929"]
      },
      {
        "time": "2020-04-19T16:00:00+03:00",
        "name": "MozgoCash: Гарри Поттер",
        "price": ["399 RUB/ком"],
        "url": ["https://quizy.pro/streams/1930"]
      },
      {
        "time": "2020-04-21T18:30:00+03:00",
        "name": "Мозгобойня live: классика #3",
        "price": ["899 RUB/ком"]
      },
      {
        "time": "2020-04-22T19:00:00+03:00",
        "name": "Мозгобойня live: классика #3",
        "price": ["899 RUB/ком"]
      },
      {
        "time": "2020-04-24T18:00:00+03:00",
        "name": "Мозгобойня live: классика #4",
        "price": ["20 EUR/ком"]
      },
      {
        "time": "2020-04-25T19:00:00+03:00",
        "name": "Мозгобойня live: День рождения Мозгобойни",
        "price": ["20 EUR/ком"]
      },
      {
        "time": "2020-04-25T17:00:00+03:00",
        "name": "MozgoCash: по сериалу Друзья",
        "price": ["399 RUB/ком"],
        "url": ["https://quizy.pro/streams/2440"]
      },
      {
        "time": "2020-05-02T18:00:00+03:00",
        "name": "MozgoCash: про кино",
        "price": ["399 RUB/ком"],
        "url": ["https://quizy.pro/streams/2680"]
      }
    ]
  }
]
