[
  {
    "org": "NeoQuiz",
    "latestCheck": "2020-04-07T12:00:00+03:00",
    "type": ["events"],
    "image": "neoquiz.png",
    "duration": 2,
    "registration": true,
    "url": ["https://vk.com/neoquiz", "http://neoquiz.ru/", "https://quizy.pro/"],
    "games": [
      {
        "time": "2020-04-02T15:00:00+03:00",
        "name": "Антивирус",
        "price": ["444 RUB/ком"],
        "url": ["https://quizy.pro/streams/1464"]
      },
      {
        "time": "2020-04-04T17:00:00+03:00",
        "name": "NeoQuiz #1 (повтор от 03.04)",
        "price": ["300 RUB/ком"],
        "url": ["https://quizy.pro/streams/1599"]
      },
      {
        "time": "2020-04-07T18:00:00+03:00",
        "name": "NeoQuiz #2 Кино",
        "price": ["149 RUB/ком"],
        "url": ["https://quizy.pro/streams/1775"]
      }
    ]
  }
]