[
  {
    "id": "9645838f-9182-4221-842c-730ddaf75f98",
    "org": "PubQuiz",
    "latestCheck": "2020-05-12T12:00:00+03:00",
    "type": ["events"],
    "image": "pubquiz.png",
    "duration": 3,
    "url": ["https://www.facebook.com/pg/PubQuiz.Me/events/", "https://online.event.in.ua/"],
    "desc": "Украинский клуб PubQuiz",
    "games": [
      {
        "time": "2020-05-07T20:00:00+03:00",
        "name": "Connection Quiz Online",
        "free": true,
        "donate": true,
        "url": ["https://www.facebook.com/events/2331358327170910"]
      },
      {
        "time": "2020-05-13T20:00:00+03:00",
        "name": "Movie Quiz Online",
        "free": true,
        "donate": true,
        "url": ["https://www.facebook.com/events/1747640092044960"]
      }
    ]
  }
]