[
  {
    "id": "371a2d78-4081-4e1e-b94e-175fbb587b21",
    "org": "Quiz Time",
    "latestCheck": "2020-05-01T12:00:00+03:00",
    "type": ["events"],
    "duration": 2,
    "image": "quiztimekr.png",
    "price": ["50 UAH/чел"],
    "url": ["https://www.facebook.com/pg/quiztime.kr/events"],
    "games": [
      {
        "time": "2020-04-18T18:30:00+03:00",
        "name": "QUIZ TIME online game",
        "url": ["https://www.facebook.com/events/532597677657659/"]
      },
      {
        "time": "2020-04-25T18:30:00+03:00",
        "name": "QUIZ TIME online game",
        "url": ["https://www.facebook.com/events/532597677657659/"]
      }
    ]
  }
]