[
  {
    "id": "ab4a284a-ea0e-4c31-9935-981d29dbdf68",
    "org": "СибКвиз",
    "latestCheck": "2020-08-14T12:00:00+03:00",
    "type": ["events"],
    "image": "sibkviz.png",
    "duration": 2,
    "price": ["300 RUB/ком"],
    "url": ["https://vk.com/sibquiz", "https://quizy.pro/"],
    "games": [
      { "time": "2020-08-02T13:00:00Z", "name": "СибКвиз Онлайн #36", "price": [ "400 RUB/ком" ], "url": [ "https://quizy.pro/streams/7400" ], "qpid": "7400", "qpuid": "2070", "qpuname": "СибКвиз", "cat": "common_knowledge" },
      { "time": "2020-08-02T16:00:00Z", "name": "СибКвиз Онлайн #36", "price": [ "400 RUB/ком" ], "url": [ "https://quizy.pro/streams/7401" ], "qpid": "7401", "qpuid": "2070", "qpuname": "СибКвиз", "cat": "common_knowledge" },
      { "time": "2020-08-04T13:00:00Z", "name": "СибКвиз Фарш#2", "price": [ "400 RUB/ком" ], "url": [ "https://quizy.pro/streams/7579" ], "qpid": "7579", "qpuid": "2070", "qpuname": "СибКвиз", "cat": "common_knowledge" },
      { "time": "2020-08-04T16:00:00Z", "name": "СибКвиз Фарш#2", "price": [ "400 RUB/ком" ], "url": [ "https://quizy.pro/streams/7580" ], "qpid": "7580", "qpuid": "2070", "qpuname": "СибКвиз", "cat": "common_knowledge" },
      { "time": "2020-08-07T13:00:00Z", "name": "СибКвиз ЗеБест#5", "price": [ "400 RUB/ком" ], "url": [ "https://quizy.pro/streams/7581" ], "qpid": "7581", "qpuid": "2070", "qpuname": "СибКвиз", "cat": "common_knowledge" },
      { "time": "2020-08-07T16:00:00Z", "name": "СибКвиз Зебест#5", "price": [ "400 RUB/ком" ], "url": [ "https://quizy.pro/streams/7582" ], "qpid": "7582", "qpuid": "2070", "qpuname": "СибКвиз", "cat": "common_knowledge" },
      { "time": "2020-08-09T13:00:00Z", "name": "СибКвиз Онлайн#38", "price": [ "400 RUB/ком" ], "url": [ "https://quizy.pro/streams/7670" ], "qpid": "7670", "qpuid": "2070", "qpuname": "СибКвиз", "cat": "common_knowledge" },
      { "time": "2020-08-09T16:00:00Z", "name": "СибКвиз Онлайн#38", "price": [ "400 RUB/ком" ], "url": [ "https://quizy.pro/streams/7671" ], "qpid": "7671", "qpuid": "2070", "qpuname": "СибКвиз", "cat": "common_knowledge" },
      { "time": "2020-08-11T15:00:00Z", "name": "СибКвиз Олимпийская#2", "price": [ "500 RUB/ком" ], "url": [ "https://quizy.pro/streams/7757" ], "qpid": "7757", "qpuid": "2070", "qpuname": "СибКвиз", "cat": "common_knowledge" },
      { "time": "2020-08-14T13:00:00Z", "name": "СибКвиз Онлайн#39", "price": [ "400 RUB/ком" ], "url": [ "https://quizy.pro/streams/7727" ], "qpid": "7727", "qpuid": "2070", "qpuname": "СибКвиз", "cat": "common_knowledge" },
      { "time": "2020-08-14T16:00:00Z", "name": "СибКвиз Онлайн#39", "price": [ "400 RUB/ком" ], "url": [ "https://quizy.pro/streams/7728" ], "qpid": "7728", "qpuid": "2070", "qpuname": "СибКвиз", "cat": "common_knowledge" },
      { "time": "2020-08-16T13:00:00Z", "name": "СибКвиз Онлайн#40", "price": [ "400 RUB/ком" ], "url": [ "https://quizy.pro/streams/7729" ], "qpid": "7729", "qpuid": "2070", "qpuname": "СибКвиз", "cat": "common_knowledge" },
      { "time": "2020-08-16T16:00:00Z", "name": "СибКвиз Онлайн#40", "price": [ "400 RUB/ком" ], "url": [ "https://quizy.pro/streams/7730" ], "qpid": "7730", "qpuid": "2070", "qpuname": "СибКвиз", "cat": "common_knowledge" }
    ]
  }
]
