[
  {
    "id": "c3b6e2fe-54fa-410c-a208-975fe848678c",
    "noOnline": true,
    "org": "ВертиGO",
    "latestCheck": "2021-03-01T12:00:00+03:00",
    "type": ["events"],
    "image": "vertigo.png",
    "duration": 1.5,
    "url": ["https://vk.com/vertigoquiz"],
    "games": [
      { "time": "2021-01-07T18:00:00+03:00", "name": "ВертиGO ONLINE", "price": ["500 RUB/ком"], "url": ["https://vk.com/wall-144404394_18281"] },
      { "time": "2021-02-22T16:00:00Z", "name": "ВертиGO Футбол #2", "price": [ "400 RUB/ком" ], "url": [ "https://quizy.pro/streams/11329" ], "qpid": "11329", "qpuid": "2783", "qpuname": "ВертиGO", "cat": "sports" }
    ]
  }
]
